specmatic_python/__init__.py
specmatic_python/utils.py
specmatic_python/version.py
specmatic_python/generators/__init__.py
specmatic_python/generators/pytest_generator.py
specmatic_python/generators/test_generator_base.py
specmatic_python/generators/unittest_generator.py
specmatic_python/server/__init__.py
specmatic_python/server/flask_server.py
specmatic_python/server/server_thread.py
specmatic_python/specmatic/__init__.py
specmatic_python/specmatic/decorators.py
specmatic_python/specmatic/specmatic.jar
specmatic_python/specmatic/specmatic.py
specmatic_python/specmatic/specmatic_runner.py
specmatic_python/specmatic/specmatic_stub.py
test/__init__.py
test/test_contract_with_pytest.py
test/test_contract_with_stub_pytest.py
test/test_contract_with_unittest.py
specmatic_python-0.2.2.dist-info/METADATA
specmatic_python-0.2.2.dist-info/WHEEL
specmatic_python-0.2.2.dist-info/top_level.txt
specmatic_python-0.2.2.dist-info/RECORD
