Metadata-Version: 2.1
Name: specmatic-python
Version: 0.2.2
Summary: A Python module for using the Specmatic Library.
Home-page: https://github.com/znsio/specmatic-python-extensions
Author: Specmatic Builders
Author-email: info@specmatic.in
Requires-Dist: blinker (==1.6.2)
Requires-Dist: click (==8.1.3)
Requires-Dist: Flask (==2.3.2)
Requires-Dist: iniconfig (==2.0.0)
Requires-Dist: itsdangerous (==2.1.2)
Requires-Dist: Jinja2 (==3.1.2)
Requires-Dist: MarkupSafe (==2.1.2)
Requires-Dist: packaging (==23.1)
Requires-Dist: pluggy (==1.0.0)
Requires-Dist: pytest (==7.3.1)
Requires-Dist: Werkzeug (==2.3.3)
